{
    "Enriched_target_attribute": "BondInstrument_enriched.duration",
    "type": "double",
    "reg_references":[
                      [
                          {
                            "type"  : "official_web_address",
                            "value" : "https://www.eba.europa.eu/documents/10180/2751085/Annex+VI+%28Annex+25+%28LCR%29%29.pdf"
                          },
                          {
                            "type"  : "Article", 
                            "value" : "325"
                          },
                          {
                              "type": "Numeric_Paragraph",
                              "value": "1"
                          },
                          {
                              "type" : "Letter_Paragraph", 
                              "value" : "a"
                          }
                      ],
                      [
                          
                          {
                            "type"  : "Article", 
                            "value" : "Article 325 approaches for calculating the own funds requirements for market risk"
                          },
                          {
                              "type": "Numeric_Paragraph",
                              "value": "1"
                          },
                          {
                              "type" : "Letter_Paragraph", 
                              "value" : "a"
                          }
                      ]
                    ]
}
