<?xml version = '1.0' encoding = 'UTF-8'?>
<Relation class="oracle.dbtools.crest.model.design.logical.Relation" name="Delta sensitivity combinations" directorySegmentName="seg_0" id="30856B2F-8B5D-5797-3B69-F42CC7E6F592">
<createdBy>Neil</createdBy>
<createdTime>2022-04-17 04:48:07 UTC</createdTime>
<ownerDesignName>frtb</ownerDesignName>
<engineerTo>
<item key="70F13CD1-1626-C0DF-DD93-774769AED5DC" value="true"/>
<item key="BEC051E3-3FE9-A559-4EC2-9F83E629BB21" value="true"/>
</engineerTo>
<targetPk>BE020382-7F9B-CD6E-595C-04A745B06A41</targetPk>
<identifying>false</identifying>
<optionalSource>true</optionalSource>
<optionalTarget>false</optionalTarget>
<sourceCardinality>*</sourceCardinality>
<sourceEntity>D696800F-974A-9206-9F17-A4CCBE2FD543</sourceEntity>
<targetCardinalityString>1</targetCardinalityString>
<targetEntity>759B8717-A824-710D-F330-8402AA7CA111</targetEntity>
<transferable>true</transferable>
<deleteRule>NO ACTION</deleteRule>
</Relation>
